[
    {
        "name": "Phoebe Buffay",
        "career": "Masseuse",
        "hobby": "Guitar, Singing",
        "image": "/friends/phoebe.png"
    },
    {
        "name": "Chandler Bing",
        "career": "Advertising Copywriter",
        "hobby": "Jokes, Foosball",
        "image": "/friends/chandler.png"
    },
    {
        "name": "Joey Tribianni",
        "career": "Actor",
        "hobby": "Food, Baywatch",
        "image": "/friends/joey.png"
    },
    {
        "name": "Monica Geller",
        "career": "Head Chef",
        "hobby": "Cleaning, Organizing",
        "image": "/friends/monica.png"
    },
    {
        "name": "Rachel Green",
        "career": "Fashion Executive",
        "hobby": "Shopping, Cheese Cake",
        "image": "/friends/rachel.png"
    },
    {
        "name": "Ross Geller",
        "career": "Paleontologist",
        "hobby": "Dinosaurs, Fossils, Piano",
        "image": "/friends/ross.png"
    }
]